{
	"projects": [
		{
			"position": [
				0,
				0,
				0
			],
			"euler": [
				0,
				0,
				0
			],
			"scale": [
				1,
				1,
				1
			],
			"name": "Demo3",
			"objectOverride": [
				{
					"path": "/root",
					"components": [
						{
							"name": "BLidgeClient",
							"props": {
								"enabled": true,
								"mode": "websocket",
								"gltf": false,
								"websocket/url": "ws://localhost:3100"
							}
						},
						{
							"name": "Music",
							"props": {
								"enabled": true
							}
						}
					]
				},
				{
					"path": "/root/blidgeRoot/MainObj/Confrict1",
					"components": [
						{
							"name": "Confrict1",
							"props": {
								"enabled": true
							}
						}
					]
				},
				{
					"path": "/root/blidgeRoot/MainObj/Confrict2",
					"components": [
						{
							"name": "Confrict2",
							"props": {
								"enabled": true
							}
						}
					]
				},
				{
					"path": "/root/blidgeRoot/MainObj/Decompty",
					"components": [
						{
							"name": "Decompty",
							"props": {
								"enabled": true
							}
						}
					]
				},
				{
					"path": "/root/blidgeRoot/MainObj/OreGL",
					"components": [
						{
							"name": "OreGL",
							"props": {
								"enabled": true
							}
						}
					]
				},
				{
					"path": "/root/blidgeRoot/MainObj/OreGL/OreGLBG",
					"components": [
						{
							"name": "OreGLBG",
							"props": {
								"enabled": true
							}
						}
					]
				},
				{
					"path": "/root/blidgeRoot/MainObj/Recollection",
					"components": [
						{
							"name": "Recollection",
							"props": {
								"enabled": true
							}
						}
					]
				},
				{
					"path": "/root/blidgeRoot/MainObj/SetA",
					"components": [
						{
							"name": "SetA",
							"props": {
								"enabled": true
							}
						}
					]
				},
				{
					"path": "/root/blidgeRoot/MainObj/Tree",
					"components": [
						{
							"name": "Tree",
							"props": {
								"enabled": true,
								"root/num": 1,
								"root/up": 0.92,
								"branch/num": 6,
								"branch/depth": 5,
								"branch/start": 0.26,
								"branch/end": 0.93,
								"branch/up": 0.2,
								"branch/wide": 1,
								"branch/curve": 0.26,
								"branch/lengthMultiplier": 1.01,
								"branch/lengthRandom": 0.5,
								"shape/length": 1.02,
								"shape/radius": 0.05,
								"shape/rootlenghRatio": 1.6,
								"shape/rootRadiusRatio": 1.6,
								"leaf/num": 9,
								"leaf/size": 0.11,
								"leaf/dpeth": 5,
								"leaf/start": 0.1,
								"seed": 14
							}
						}
					]
				},
				{
					"path": "/root/blidgeRoot/SkyBox",
					"components": [
						{
							"name": "SkyBoxDemo3",
							"props": {
								"enabled": true
							}
						}
					]
				},
				{
					"path": "/root/blidgeRoot/Stage/Boxes",
					"components": [
						{
							"name": "Boxes",
							"props": {
								"enabled": true
							}
						}
					]
				},
				{
					"path": "/root/blidgeRoot/Stage/Circles",
					"components": [
						{
							"name": "Circles",
							"props": {
								"enabled": true
							}
						}
					]
				},
				{
					"path": "/root/blidgeRoot/Stage/Erode",
					"components": [
						{
							"name": "Erode",
							"props": {
								"enabled": true
							}
						}
					]
				},
				{
					"path": "/root/blidgeRoot/Stage/Flower",
					"components": [
						{
							"name": "Flower",
							"props": {
								"enabled": true
							}
						}
					]
				},
				{
					"path": "/root/blidgeRoot/Stage/Grid",
					"components": [
						{
							"name": "Grid",
							"props": {
								"enabled": true
							}
						}
					]
				},
				{
					"path": "/root/blidgeRoot/Stage/Ring",
					"components": [
						{
							"name": "Ring",
							"props": {
								"enabled": true
							}
						}
					]
				},
				{
					"path": "/root/blidgeRoot/Stage/Tornado",
					"components": [
						{
							"name": "Tornado",
							"props": {
								"enabled": true
							}
						}
					]
				},
				{
					"path": "/root/blidgeRoot/Stage/Wave",
					"components": [
						{
							"name": "Wave",
							"props": {
								"enabled": true
							}
						}
					]
				}
			],
			"scene": {
				"name": "root",
				"childs": [
					{
						"name": "Test"
					}
				]
			},
			"timeline/duration": 5092,
			"timeline/fps": 30
		},
		{
			"position": [
				0,
				0,
				0
			],
			"euler": [
				0,
				0,
				0
			],
			"scale": [
				1,
				1,
				1
			],
			"name": "New Project",
			"objectOverride": [
				{
					"path": "/root/test",
					"components": [
						{
							"name": "TuringRenderer",
							"props": {
								"enabled": true,
								"f": {
									"value": {
										"value": {
											"value": 0.016
										}
									}
								},
								"k": {
									"value": {
										"value": {
											"value": 0.043
										}
									}
								}
							}
						},
						{
							"name": "CubeGeometry",
							"props": {
								"enabled": true
							}
						}
					]
				},
				{
					"path": "/root/Light",
					"components": [
						{
							"name": "Light",
							"props": {
								"enabled": true,
								"lightType": "directional",
								"color": {
									"x": 1,
									"y": 1,
									"z": 1,
									"w": 0
								},
								"intensity": 1,
								"angle": 50,
								"blend": 1,
								"distance": 30,
								"decay": 2,
								"castShadow": false
							}
						}
					]
				}
			],
			"scene": {
				"name": "root",
				"childs": [
					{
						"name": "test"
					},
					{
						"name": "Light",
						"pos": [
							0,
							3.049999999999999,
							0
						],
						"scale": [
							0.6999999999999998,
							1,
							1
						]
					}
				]
			},
			"timeline/duration": 10185,
			"timeline/fps": 60
		}
	],
	"enableRender": true,
	"projectName": "Demo3",
	"openedProject": "Demo3",
	"resolutionScale": 0.5,
	"viewType": "render",
	"frameLoop/enabled": false,
	"frameLoop/start": 3501.109604519774,
	"frameLoop/end": 4375.630081288137,
	"selectedEntity": "8d"
}